screen2table/__init__.py
screen2table/configs.cfg
screen2table/helpers.py
screen2table/screen2table.py
screen2table-0.3.0.post1.dist-info/LICENSE
screen2table-0.3.0.post1.dist-info/METADATA
screen2table-0.3.0.post1.dist-info/WHEEL
screen2table-0.3.0.post1.dist-info/entry_points.txt
screen2table-0.3.0.post1.dist-info/top_level.txt
screen2table-0.3.0.post1.dist-info/RECORD
