Metadata-Version: 2.1
Name: screen2table
Version: 0.3.0.post1
Summary: A Windows GUI app to generate geometric data table by tracing shapes displayed on the screen.
Home-page: https://github.com/maximlt/screen2table
Author: Maxime Liquet
Author-email: maximeliquet@free.fr
License: MIT
Platform: UNKNOWN
Classifier: License :: OSI Approved :: MIT License
Classifier: Operating System :: Microsoft :: Windows
Classifier: Programming Language :: Python :: 3
Classifier: Programming Language :: Python :: 3.7
Classifier: Topic :: Scientific/Engineering :: Hydrology
Requires-Python: ~=3.7
Requires-Dist: matplotlib (==3.1.1)
Requires-Dist: numpy (==1.15.4)
Requires-Dist: pywin32 (==224)
Requires-Dist: pynput (==1.4.4)
